{
    "key": "group_55f1bdb883d67",
    "title": "FAQ",
    "fields": [
        {
            "key": "field_55f1bddda8b77",
            "label": "FAQ is header",
            "name": "faq_is_header",
            "type": "true_false",
            "instructions": "This will render the item as a header using the title and not showing any of the content.",
            "required": 0,
            "conditional_logic": 0,
            "wrapper": {
                "width": "",
                "class": "",
                "id": ""
            },
            "message": "",
            "default_value": 0
        }
    ],
    "location": [
        [
            {
                "param": "post_type",
                "operator": "==",
                "value": "faq"
            }
        ]
    ],
    "menu_order": 0,
    "position": "normal",
    "style": "default",
    "label_placement": "top",
    "instruction_placement": "label",
    "hide_on_screen": [
        "permalink",
        "excerpt",
        "custom_fields",
        "discussion",
        "comments",
        "revisions",
        "author",
        "format",
        "page_attributes",
        "featured_image",
        "categories",
        "tags",
        "send-trackbacks"
    ],
    "active": 1,
    "description": "",
    "modified": 1441906282
}